easy_redis/__init__.py
easy_redis/redis_config.py
easy_redis/redis_conn.py
easy_redis/redis_consumer.py
easy_redis/redis_log.py
easy_redis/redis_producer.py
easy_redis-0.0.4.dist-info/METADATA
easy_redis-0.0.4.dist-info/WHEEL
easy_redis-0.0.4.dist-info/top_level.txt
easy_redis-0.0.4.dist-info/RECORD
